LICENSE
MANIFEST.in
README.md
pyproject.toml
setup.py
kmv/__init__.py
kmv/py.typed
kmv/requirements-dev.txt
kmv/requirements.txt
kmv.egg-info/PKG-INFO
kmv.egg-info/SOURCES.txt
kmv.egg-info/dependency_links.txt
kmv.egg-info/requires.txt
kmv.egg-info/top_level.txt
kmv/app/__init__.py
kmv/app/viewer.py
kmv/core/__init__.py
kmv/core/controller.py
kmv/core/ring.py
kmv/core/streams.py
kmv/core/types.py
kmv/ipc/__init__.py
kmv/ipc/control.py
kmv/ipc/shared_ring.py
kmv/ui/__init__.py
kmv/ui/help.py
kmv/ui/plot.py
kmv/ui/settings.py
kmv/ui/table.py
kmv/ui/viewport.py
kmv/utils/__init__.py
kmv/utils/geometry.py
kmv/utils/logging.py
kmv/worker/__init__.py
kmv/worker/entrypoint.py
kmv/worker/window.py
tests/test_dummy.py