Metadata-Version: 2.4
Name: kmv
Version: 0.3.22
Summary: The kscale-mujoco-viewer project
Home-page: https://github.com/kscalelabs/kscale-mujoco-viewer
Author: Ali Kuwajerwala, Wesley Maa
Requires-Python: >=3.11
License-File: LICENSE
Requires-Dist: mujoco
Requires-Dist: PySide6==6.9.0
Requires-Dist: pyqtgraph
Requires-Dist: colorlogging
Provides-Extra: dev
Requires-Dist: black; extra == "dev"
Requires-Dist: darglint; extra == "dev"
Requires-Dist: mypy; extra == "dev"
Requires-Dist: pytest; extra == "dev"
Requires-Dist: ruff; extra == "dev"
Dynamic: author
Dynamic: description
Dynamic: description-content-type
Dynamic: home-page
Dynamic: license-file
Dynamic: provides-extra
Dynamic: requires-dist
Dynamic: requires-python
Dynamic: summary
